rfc8785/__init__.py
rfc8785/_impl.py
rfc8785/py.typed
rfc8785-0.1.3.dist-info/LICENSE
rfc8785-0.1.3.dist-info/WHEEL
rfc8785-0.1.3.dist-info/METADATA
rfc8785-0.1.3.dist-info/RECORD
