Metadata-Version: 2.1
Name: rfc8785
Version: 0.1.3
Summary: A pure-Python implementation of RFC 8785 (JSON Canonicalization Scheme)
Author-email: Trail of Bits <opensource@trailofbits.com>
Requires-Python: >=3.8
Classifier: Development Status :: 4 - Beta
Classifier: License :: OSI Approved :: Apache Software License
Classifier: Programming Language :: Python :: 3
Classifier: Topic :: File Formats :: JSON
Classifier: Topic :: Security :: Cryptography
Requires-Dist: rfc8785[doc,test,lint] ; extra == "dev"
Requires-Dist: build ; extra == "dev"
Requires-Dist: pdoc ; extra == "doc"
Requires-Dist: ruff ~= 0.3 ; extra == "lint"
Requires-Dist: mypy >= 1.0 ; extra == "lint"
Requires-Dist: interrogate ; extra == "lint"
Requires-Dist: pytest ; extra == "test"
Requires-Dist: pytest-cov ; extra == "test"
Requires-Dist: coverage ; extra == "test"
Project-URL: Documentation, https://trailofbits.github.io/rfc8785.py/
Project-URL: Homepage, https://pypi.org/project/rfc8785
Project-URL: Issues, https://github.com/trailofbits/rfc8785.py/issues
Project-URL: Source, https://github.com/trailofbits/rfc8785.py
Provides-Extra: dev
Provides-Extra: doc
Provides-Extra: lint
Provides-Extra: test
